Metadata-Version: 2.1
Name: nato-cli
Version: 0.0.1
Summary: Allows quick translation of a string to its letters in NATO form.
Home-page: https://github.com/seaty6/nato-cli
Author: Sampath Eaty
Author-email: s.eaty6@gmail.com
License: UNKNOWN
Platform: UNKNOWN
Classifier: License :: OSI Approved :: MIT License
Classifier: Programming Language :: Python
Classifier: Programming Language :: Python :: 3
Classifier: Programming Language :: Python :: 3.6
Classifier: Programming Language :: Python :: 3.7
Classifier: Programming Language :: Python :: 3.8
Classifier: Programming Language :: Python :: 3.9
Classifier: Operating System :: OS Independent
Classifier: Environment :: Console
Classifier: Intended Audience :: End Users/Desktop
